LICENSE
MANIFEST.in
README.md
setup.py
channels_jsonrpc/__init__.py
channels_jsonrpc/jsonrpcconsumer.py
django_channels2_jsonrpc.egg-info/PKG-INFO
django_channels2_jsonrpc.egg-info/SOURCES.txt
django_channels2_jsonrpc.egg-info/dependency_links.txt
django_channels2_jsonrpc.egg-info/requires.txt
django_channels2_jsonrpc.egg-info/top_level.txt